odoo/addons/stock_picking_filter_product/README.rst
odoo/addons/stock_picking_filter_product/__init__.py
odoo/addons/stock_picking_filter_product/__manifest__.py
odoo/addons/stock_picking_filter_product/i18n/stock_picking_filter_product.pot
odoo/addons/stock_picking_filter_product/models/__init__.py
odoo/addons/stock_picking_filter_product/models/product_product.py
odoo/addons/stock_picking_filter_product/readme/CONTRIBUTORS.rst
odoo/addons/stock_picking_filter_product/readme/DESCRIPTION.rst
odoo/addons/stock_picking_filter_product/readme/USAGE.rst
odoo/addons/stock_picking_filter_product/static/description/icon.png
odoo/addons/stock_picking_filter_product/static/description/index.html
odoo/addons/stock_picking_filter_product/views/stock_picking_view.xml
odoo/addons/stock_picking_filter_product/views/stock_scrap_view.xml
odoo12_addon_stock_picking_filter_product-12.0.1.0.0.99.dev3.dist-info/METADATA
odoo12_addon_stock_picking_filter_product-12.0.1.0.0.99.dev3.dist-info/WHEEL
odoo12_addon_stock_picking_filter_product-12.0.1.0.0.99.dev3.dist-info/top_level.txt
odoo12_addon_stock_picking_filter_product-12.0.1.0.0.99.dev3.dist-info/RECORD
